fmod_toolkit/fmod.py
fmod_toolkit/__init__.py
fmod_toolkit/importer.py
fmod_toolkit/libfmod/Linux/x86/libfmod.so
fmod_toolkit-0.1.3.dist-info/LICENSE
fmod_toolkit-0.1.3.dist-info/WHEEL
fmod_toolkit-0.1.3.dist-info/top_level.txt
fmod_toolkit-0.1.3.dist-info/METADATA
fmod_toolkit-0.1.3.dist-info/RECORD
