Metadata-Version: 2.4
Name: fmod_toolkit
Version: 0.1.3
Author-email: Rudolf Kolbe <rkolbe96@gmail.com>
License: MIT License
Project-URL: Homepage, https://github.com/K0lb3/fmod_toolkit
Project-URL: Bug Tracker, https://github.com/K0lb3/fmod_toolkit/issues
Classifier: License :: OSI Approved :: MIT License
Classifier: Operating System :: OS Independent
Classifier: Intended Audience :: Developers
Classifier: Development Status :: 5 - Production/Stable
Classifier: Programming Language :: Python
Classifier: Programming Language :: Python :: 3
Classifier: Topic :: Software Development :: Libraries :: Python Modules
Classifier: Topic :: Games/Entertainment
Requires-Python: >=3.8
License-File: LICENSE
Requires-Dist: pyfmodex>=0.7.2
Provides-Extra: tests
Requires-Dist: pytest; extra == "tests"
Provides-Extra: dev
Requires-Dist: ruff; extra == "dev"
Requires-Dist: fmod_toolkit[tests]; extra == "dev"
Dynamic: license-file
